kelly_cli/__init__.py
kelly_cli/kelly.py
kelly_cli-0.3.1.dist-info/entry_points.txt
kelly_cli-0.3.1.dist-info/METADATA
kelly_cli-0.3.1.dist-info/WHEEL
kelly_cli-0.3.1.dist-info/RECORD
