Metadata-Version: 2.1
Name: kelly-cli
Version: 0.3.1
Summary: A command line tool for calculating the Kelly Criterion betting stake for given odds and bank size
Author: peaky76
Author-email: robertjamespeacock@gmail.com
Requires-Python: >=3.11,<4.0
Classifier: Programming Language :: Python :: 3
Classifier: Programming Language :: Python :: 3.11
Requires-Dist: click (>=8.1.3,<9.0.0)
Requires-Dist: pybet (>=0.8,<0.9)
